Workbook

Sheet тонн
F1: Тонн | G1: Цена | H1: Сумма | I1: Остатка Нурбек
E2: Жами юк | F2: 0 | H2: =+SUM(H4:H19) -> 0 | I2: 77200000
E4: 17,08,2026 | F4: =+F2-SUM(F5:F19) -> 0 | G4: 3720 | H4: =+F4*G4 -> 0 | I4: 10550-15000-8350=7720000
H5: =+F5*G5 -> 0
H6: =+F6*G6 -> 0
H7: =+F7*G7 -> 0
H8: =+F8*G8 -> 0
H9: =+F9*G9 -> 0
H10: =+F10*G10 -> 0
H11: =+F11*G11 -> 0
H12: =+F12*G12 -> 0
H13: =+F13*G13 -> 0
H14: =+F14*G14 -> 0
H15: =+F15*G15 -> 0
H16: =+F16*G16 -> 0
... H19: =+F19*G19 -> 0

Sheet Хитой
A1: Дата | B1: Итог дня
B2: Хитой пул | C2: Ойбек юк | D2: Нурбек тонн | E2: Нурбек Харажат | F2: Фарход тонн | G2: Фарход харажат | H2: Итого | I2: Бригад | J2: Фазли | K2: Нурбек | L2: Лишный расход | M2: Фойда
C3: =+тонн!H2 -> 0 | D3: =+тонн!F2 -> 0
B4: Утган ойдан хитой карзи | C4: 0
A5: 46235 | H5: =+D5+F5 -> 0 | M5: =+C5-E5-G5-I5-J5-K5-L5 -> 0
A6: =+A5+1 -> 46236 | H6: =+D6+F6 -> 0 | M6: =+C6-E6-G6-I6-J6-K6-L6 -> 0
A7: =+A6+1 -> 46237 | H7: =+D7+F7 -> 0 | M7: =+C7-E7-G7-I7-J7-K7-L7 -> 0
A8: =+A7+1 -> 46238 | H8: =+D8+F8 -> 0 | M8: =+C8-E8-G8-I8-J8-K8-L8 -> 0
A9: =+A8+1 -> 46239 | H9: =+D9+F9 -> 0 | M9: =+C9-E9-G9-I9-J9-K9-L9 -> 0
A10: =+A9+1 -> 46240 | H10: =+D10+F10 -> 0 | M10: =+C10-E10-G10-I10-J10-K10-L10 -> 0
A11: =+A10+1 -> 46241 | H11: =+D11+F11 -> 0 | M11: =+C11-E11-G11-I11-J11-K11-L11 -> 0
A12: =+A11+1 -> 46242 | H12: =+D12+F12 -> 0 | M12: =+C12-E12-G12-I12-J12-K12-L12 -> 0
A13: =+A12+1 -> 46243 | H13: =+D13+F13 -> 0 | M13: =+C13-E13-G13-I13-J13-K13-L13 -> 0
A14: =+A13+1 -> 46244 | H14: =+D14+F14 -> 0 | M14: =+C14-E14-G14-I14-J14-K14-L14 -> 0
A15: =+A14+1 -> 46245 | H15: =+D15+F15 -> 0 | M15: =+C15-E15-G15-I15-J15-K15-L15 -> 0
A16: =+A15+1 -> 46246 | H16: =+D16+F16 -> 0 | M16: =+C16-E16-G16-I16-J16-K16-L16 -> 0
A17: =+A16+1 -> 46247 | H17: =+D17+F17 -> 0 | M17: =+C17-E17-G17-I17-J17-K17-L17 -> 0
... A35: =+A34+1 -> 46265 | H35: =+D35+F35 -> 0 | M35: =+C35-E35-G35-I35-J35-K35-L35 -> 0
B36: =+SUM(B3:B35) -> 0 | C36: =+SUM(C4:C35) -> 0 | D36: =+SUM(D5:D35) -> 0 | E36: =+SUM(E5:E35) -> 0 | F36: =+SUM(F3:F35) -> 0 | G36: =+SUM(G3:G35) -> 0 | H36: =+SUM(H3:H35) -> 0 | I36: =+SUM(I3:I35) -> 0 | J36: =+SUM(J3:J35) -> 0 | K36: =+SUM(K3:K35) -> 0 | L36: =+SUM(L3:L35) -> 0 | M36: =+SUM(M3:M35) -> 0
B38: Хитой | C38: =+B36-C36 -> 0
B39: Ойбек | C39: =+C36-B36 -> 0
B40: Тоннаж | C40: =+H36 -> 0
B41: Фойда | C41: =+M36 -> 0
B43: Ойбек | C43: =+C36 -> 0
B44: Нурбек харид | C44: =+E36 -> 0
B45: Бригад | C45: =+I36 -> 0
B46: Фазли | C46: =+J36 -> 0
B47: Лишный расход | C47: =+L36 -> 0
B48: Нурбек ойлик | C48: =+K36 -> 0
B49: Хитой итого долг | C49: =+C50+C39 -> 0
B50: Хитой бонус | C50: =+C40*100 -> 0
B51: Соф фойда | C51: =+C50+C41 -> 0
B52: ИКРОМ | C52: =+C40*20 -> 0
C53: =+C41*20 -> 0
C54: =+C42*20 -> 0
C55: =+C43*20 -> 0
C56: =+C44*20 -> 0
B58: Итого | C58: =+C51-C52-C53-C54-C55-C56-C57 -> 0
B59: Ойбек | C59: =+C58/3 -> 0
B60: Тура ака | C60: =+C58/3 -> 0
B61: Рустам | C61: =+C58/3 -> 0

Sheet тура ака
A1: Дата | B1: Ойбек Пул берди | C1: Тура ака Пул берди | D1: Нима учун берди | E1: Номер машини | F1: Брутто | G1: Тара | H1: Нетто | I1: % скидка | J1: Чистый | K1: Цена | L1: сумма Металл | M1: Ойбек пул берди | N1: =+N2+B3 -> 1.1849354e+09 | P1: Ойбек пул | Q1: Фойда
M2: Ойбек | N2: =+L3-C3 -> 7.2443744e+08
B3: =+SUM(B4:B9995) -> 460497948 | C3: =+SUM(C4:C9995) -> 24681400060 | F3: =+SUM(F4:F9995) -> 13815660 | G3: =+SUM(G4:G9995) -> 6833940 | H3: =+SUM(H4:H9995) -> 6981720 | J3: =+SUM(J4:J9995) -> 6828721.2 | L3: =+SUM(L4:L9995)+857286788 -> 2.5405838e+10 | M3: Тура | N3: =+C3-L3-B3 -> -1.1849354e+09
A4: 01,02,2026 | C4: 955000 | D4: 834 зарар | E4: 966 бекобод | F4: 27180 | G4: 13460 | H4: =+F4-G4 -> 13720 | I4: 3 | J4: =+H4-H4*I4/100 -> 13308.4 | K4: 3350 | L4: =+J4*K4 -> 44583140
C5: 120000000 | D5: сум | E5: 004 тур мяхки | F5: 22050 | G5: 9970 | H5: =+F5-G5 -> 12080 | I5: 2 | J5: =+H5-H5*I5/100 -> 11838.4 | K5: 3650 | L5: =+J5*K5 -> 43210160
C6: 36065000 | D6: хитой чермет | H6: =+F6-G6 -> 0 | J6: =+H6-H6*I6/100 -> 0 | L6: =+J6*K6 -> 0
A7: 2,02,2026 | C7: 242000000 | D7: икром симентчи | E7: 264 мяхки нов | F7: 23140 | G7: 10880 | H7: =+F7-G7 -> 12260 | I7: 2 | J7: =+H7-H7*I7/100 -> 12014.8 | K7: 3650 | L7: =+J7*K7 -> 43854020
E8: 388 релс | F8: 30000 | G8: 10170 | H8: =+F8-G8 -> 19830 | J8: =+H8-H8*I8/100 -> 19830 | K8: 3650 | L8: =+J8*K8 -> 72379500
E9: 142 релс | F9: 39910 | G9: 13310 | H9: =+F9-G9 -> 26600 | J9: =+H9-H9*I9/100 -> 26600 | K9: 3650 | L9: =+J9*K9 -> 97090000
E10: 130 релс | F10: 26720 | G10: 9580 | H10: =+F10-G10 -> 17140 | J10: =+H10-H10*I10/100 -> 17140 | K10: 3650 | L10: =+J10*K10 -> 62561000
C11: 3370000 | D11: 266 зарар+++ | E11: 884 чугун бекобод | F11: 37120 | G11: 13380 | H11: =+F11-G11 -> 23740 | I11: 2 | J11: =+H11-H11*I11/100 -> 23265.2 | K11: 3350 | L11: =+J11*K11 -> 77938420
A12: 3,02,2026 | E12: 365 бекобод | F12: 26180 | G12: 12980 | H12: =+F12-G12 -> 13200 | I12: 2 | J12: =+H12-H12*I12/100 -> 12936 | K12: 3350 | L12: =+J12*K12 -> 43335600
E13: 377 бозор чирчик | F13: 25480 | G13: 9460 | H13: =+F13-G13 -> 16020 | I13: 1 | J13: =+H13-H13*I13/100 -> 15859.8 | K13: 3650 | L13: =+J13*K13 -> 57888270
E14: 904 мяхки йул кир | F14: 15920 | G14: 9140 | H14: =+F14-G14 -> 6780 | I14: 2 | J14: =+H14-H14*I14/100 -> 6644.4 | K14: 3900 | L14: =+J14*K14 -> 25913160
C15: =650*3650 -> 2372500 | D15: 011 зарар | H15: =+F15-G15 -> 0 | J15: =+H15-H15*I15/100 -> 0 | L15: =+J15*K15 -> 0
A16: 4,03,2026 | C16: =40000*12250 -> 490000000 | D16: 40,000 $$ | E16: 725 мяхки ислом | F16: 10790 | G16: 4900 | H16: =+F16-G16 -> 5890 | I16: 2 | J16: =+H16-H16*I16/100 -> 5772.2 | K16: 3900 | L16: =+J16*K16 -> 22511580
E17: 074 когон мяхки | F17: 25400 | G17: 11160 | H17: =+F17-G17 -> 14240 | I17: 2 | J17: =+H17-H17*I17/100 -> 13955.2 | K17: 3600 | L17: =+J17*K17 -> 50238720
C18: 300000 | D18: 800-500=300 низ | E18: 445 мяхки низом | F18: 23820 | G18: 9240 | H18: =+F18-G18 -> 14580 | I18: 2 | J18: =+H18-H18*I18/100 -> 14288.4 | K18: 3650 | L18: =+J18*K18 -> 52152660
C19: 300000 | D19: 574 шофир | E19: 574 бобир бекобод | F19: 24980 | G19: 12900 | H19: =+F19-G19 -> 12080 | I19: 3 | J19: =+H19-H19*I19/100 -> 11717.6 | K19: 3350 | L19: =+J19*K19 -> 39253960
E20: 463 бобр мяхк | F20: 25120 | G20: 9960 | H20: =+F20-G20 -> 15160 | I20: 1 | J20: =+H20-H20*I20/100 -> 15008.4 | K20: 3650 | L20: =+J20*K20 -> 54780660
E21: 593 мяхки комил | F21: 21980 | G21: 12750 | H21: =+F21-G21 -> 9230 | I21: 2 | J21: =+H21-H21*I21/100 -> 9045.4 | K21: 3650 | L21: =+J21*K21 -> 33015710
E22: 597 тур мяхки | F22: 25530 | G22: 11460 | H22: =+F22-G22 -> 14070 | I22: 2 | J22: =+H22-H22*I22/100 -> 13788.6 | K22: 3650 | L22: =+J22*K22 -> 50328390
C23: 325000 | D23: 413 мошин | E23: 413 бекобод | F23: 25520 | G23: 14820 | H23: =+F23-G23 -> 10700 | I23: 3 | J23: =+H23-H23*I23/100 -> 10379 | K23: 3350 | L23: =+J23*K23 -> 34769650
A24: 5,02,2026 | C24: =10000*12250 -> 122500000 | E24: 145 мяхки исл | F24: 10580 | G24: 5160 | H24: =+F24-G24 -> 5420 | I24: 2 | J24: =+H24-H24*I24/100 -> 5311.6 | K24: 3900 | L24: =+J24*K24 -> 20715240
E25: 437 мяхки исл | F25: 9500 | G25: 4670 | H25: =+F25-G25 -> 4830 | I25: 2 | J25: =+H25-H25*I25/100 -> 4733.4 | K25: 3900 | L25: =+J25*K25 -> 18460260
C26: 380000 | D26: 593 шофир | E26: 562 ром мяхки | F26: 29400 | G26: 9800 | H26: =+F26-G26 -> 19600 | I26: 2 | J26: =+H26-H26*I26/100 -> 19208 | K26: 3650 | L26: =+J26*K26 -> 70109200
C27: 700000 | D27: 032 шофир | E27: 032 еко бекобод | F27: 24080 | G27: 14040 | H27: =+F27-G27 -> 10040 | I27: 3.6 | J27: =+H27-H27*I27/100 -> 9678.56 | K27: 3350 | L27: =+J27*K27 -> 32423176
A28: 6,02,2026 | C28: =16000*12270 -> 196320000 | D28: 16000$ | E28: 996 ТУР МЯХКИ | F28: 22200 | G28: 9830 | H28: =+F28-G28 -> 12370 | I28: 2 | J28: =+H28-H28*I28/100 -> 12122.6 | K28: 3650 | L28: =+J28*K28 -> 44247490 | P28: 43100000 | Q28: =+L28-P28 -> 1147490
E29: 384 бекобод | F29: 26520 | G29: 13300 | H29: =+F29-G29 -> 13220 | I29: 2.6 | J29: =+H29-H29*I29/100 -> 12876.28 | K29: 3350 | L29: =+J29*K29 -> 43135538 | P29: 42474000 | Q29: =+L29-P29 -> 661538
C30: 645000 | D30: 537 мошин учун | E30: 537 мяхки комил | F30: 17620 | G30: 10200 | H30: =+F30-G30 -> 7420 | I30: 2 | J30: =+H30-H30*I30/100 -> 7271.6 | K30: 3650 | L30: =+J30*K30 -> 26541340 | P30: 25645000 | Q30: =+L30-P30 -> 896340
C31: 365000 | D31: 377 мошин учун | E31: 377 мяхки рометан | F31: 17940 | G31: 9400 | H31: =+F31-G31 -> 8540 | I31: 2 | J31: =+H31-H31*I31/100 -> 8369.2 | K31: 3650 | L31: =+J31*K31 -> 30547580 | P31: 29525000 | Q31: =+L31-P31 -> 1022580
E32: 714 бекобод жамил | F32: 32900 | G32: 12460 | H32: =+F32-G32 -> 20440 | I32: 2.5 | J32: =+H32-H32*I32/100 -> 19929 | K32: 3350 | L32: =+J32*K32 -> 66762150 | P32: 64753000 | Q32: =+L32-P32 -> 2009150
C33: 1267000 | D33: 074 зарар | H33: =+F33-G33 -> 0 | J33: =+H33-H33*I33/100 -> 0 | L33: =+J33*K33 -> 0 | Q33: =+L33-P33 -> 0
C34: 858000 | D34: 445 зарар | H34: =+F34-G34 -> 0 | J34: =+H34-H34*I34/100 -> 0 | L34: =+J34*K34 -> 0 | Q34: =+L34-P34 -> 0
A35: 7,02,2026 | C35: =15000*12280 -> 184200000 | D35: 15000$$ | E35: 999 бекобод жамил | F35: 23900 | G35: 11000 | H35: =+F35-G35 -> 12900 | I35: 2 | J35: =+H35-H35*I35/100 -> 12642 | K35: 3350 | L35: =+J35*K35 -> 42350700 | P35: 41500000 | Q35: =+L35-P35 -> 850700
E36: 698 мяхк ислом | F36: 11160 | G36: 5020 | H36: =+F36-G36 -> 6140 | I36: 2 | J36: =+H36-H36*I36/100 -> 6017.2 | K36: 3900 | L36: =+J36*K36 -> 23467080 | P36: 22632000 | Q36: =+L36-P36 -> 835080
H37: =+F37-G37 -> 0 | J37: =+H37-H37*I37/100 -> 0 | L37: =+J37*K37 -> 0 | Q37: =+L37-P37 -> 0
C38: =288*3900 -> 1123200 | D38: 288 кг 463 мошин | H38: =+F38-G38 -> 0 | J38: =+H38-H38*I38/100 -> 0 | L38: =+J38*K38 -> 0 | Q38: =+L38-P38 -> 0
C39: =133*3900 -> 518700 | D39: 133кг 437 мошин | H39: =+F39-G39 -> 0 | J39: =+H39-H39*I39/100 -> 0 | L39: =+J39*K39 -> 0 | Q39: =+L39-P39 -> 0
C40: =278*3900 -> 1084200 | D40: 278 кг 562 мошин | H40: =+F40-G40 -> 0 | J40: =+H40-H40*I40/100 -> 0 | L40: =+J40*K40 -> 0 | Q40: =+L40-P40 -> 0
C41: =309*3900 -> 1205100 | D41: 597 мошин | H41: =+F41-G41 -> 0 | J41: =+H41-H41*I41/100 -> 0 | L41: =+J41*K41 -> 0 | Q41: =+L41-P41 -> 0
A42: 8,02,2026 | E42: 413 прес | F42: 28780 | G42: 14840 | H42: =+F42-G42 -> 13940 | I42: 5 | J42: =+H42-H42*I42/100 -> 13243 | K42: 3250 | L42: =+J42*K42 -> 43039750 | P42: 44135000 | Q42: =+L42-P42 -> -1095250
E43: 642 мяхк ром | F43: 30860 | G43: 13300 | H43: =+F43-G43 -> 17560 | I43: 2 | J43: =+H43-H43*I43/100 -> 17208.8 | K43: 3650 | L43: =+J43*K43 -> 62812120 | P43: 60230000 | Q43: =+L43-P43 -> 2582120
H44: =+F44-G44 -> 0 | J44: =+H44-H44*I44/100 -> 0 | L44: =+J44*K44 -> 0 | P44: 60500 | Q44: =+L44-P44 -> -60500
E45: 264 мяхк шамс | F45: 24210 | G45: 10820 | H45: =+F45-G45 -> 13390 | I45: 2 | J45: =+H45-H45*I45/100 -> 13122.2 | K45: 3650 | L45: =+J45*K45 -> 47896030 | P45: 46757000 | Q45: =+L45-P45 -> 1139030
E46: 057 пешку жамил | F46: 36240 | G46: 17860 | H46: =+F46-G46 -> 18380 | I46: 2 | J46: =+H46-H46*I46/100 -> 18012.4 | K46: 3350 | L46: =+J46*K46 -> 60341540 | P46: 59620000 | Q46: =+L46-P46 -> 721540
A47: 9,02,2026 | E47: 074 мяхки нов | F47: 24200 | G47: 11080 | H47: =+F47-G47 -> 13120 | I47: 2 | J47: =+H47-H47*I47/100 -> 12857.6 | K47: 3650 | L47: =+J47*K47 -> 46930240 | P47: 45383000 | Q47: =+L47-P47 -> 1547240
A48: 10,02,2026 | C48: =20000*12300 -> 246000000 | D48: 20,000 $$ 12300 к | H48: =+F48-G48 -> 0 | J48: =+H48-H48*I48/100 -> 0 | L48: =+J48*K48 -> 0 | Q48: =+L48-P48 -> 0
E49: 445 чугун тур бекобод | F49: 22990 | G49: 9200 | H49: =+F49-G49 -> 13790 | I49: 2.5 | J49: =+H49-H49*I49/100 -> 13445.25 | K49: 3350 | L49: =+J49*K49 -> 45041588 | P49: 44128000 | Q49: =+L49-P49 -> 913587.5
E50: 188 чугун тур бекобод | F50: 24080 | G50: 9930 | H50: =+F50-G50 -> 14150 | I50: 2.5 | J50: =+H50-H50*I50/100 -> 13796.25 | K50: 3350 | L50: =+J50*K50 -> 46217438 | P50: 45280000 | Q50: =+L50-P50 -> 937437.5
E51: 384 мяхк когон | F51: 24900 | G51: 13000 | H51: =+F51-G51 -> 11900 | I51: 2 | J51: =+H51-H51*I51/100 -> 11662 | K51: 3650 | L51: =+J51*K51 -> 42566300 | P51: 40608000 | Q51: =+L51-P51 -> 1958300
H52: =+F52-G52 -> 0 | J52: =+H52-H52*I52/100 -> 0 | L52: =+J52*K52 -> 0 | Q52: =+L52-P52 -> 0
H53: =+F53-G53 -> 0 | J53: =+H53-H53*I53/100 -> 0 | L53: =+J53*K53 -> 0 | Q53: =+L53-P53 -> 0
H54: =+F54-G54 -> 0 | J54: =+H54-H54*I54/100 -> 0 | L54: =+J54*K54 -> 0 | Q54: =+L54-P54 -> 0
A55: 11,02,2026 | C55: =34000*12300 -> 418200000 | D55: 34000 $ 12300 к | E55: 532 тур мяхки | F55: 18580 | G55: 9740 | H55: =+F55-G55 -> 8840 | I55: 2 | J55: =+H55-H55*I55/100 -> 8663.2 | K55: 3650 | L55: =+J55*K55 -> 31620680 | P55: 30870000 | Q55: =+L55-P55 -> 750680
E56: 996 мяхк ой | F56: 21690 | G56: 9700 | H56: =+F56-G56 -> 11990 | I56: 2 | J56: =+H56-H56*I56/100 -> 11750.2 | K56: 3650 | L56: =+J56*K56 -> 42888230 | P56: 40706000 | Q56: =+L56-P56 -> 2182230
A57: 12,02,2026 | C57: =5000*12270 -> 61350000 | D57: 5000 $ 12270 К | E57: 187 КОГОН МЯХИ | F57: 20880 | G57: 9000 | H57: =+F57-G57 -> 11880 | I57: 2 | J57: =+H57-H57*I57/100 -> 11642.4 | K57: 3650 | L57: =+J57*K57 -> 42494760 | P57: 40608000 | Q57: =+L57-P57 -> 1886760
E58: 184 ЧУГУН НИЗОМ | F58: 26100 | G58: 12280 | H58: =+F58-G58 -> 13820 | I58: 2.5 | J58: =+H58-H58*I58/100 -> 13474.5 | K58: 3350 | L58: =+J58*K58 -> 45139575 | P58: 43780000 | Q58: =+L58-P58 -> 1359575
A59: 13,02,2026 | C59: 250000 | D59: 368 мошин учун | E59: 229 мяхки фармон | F59: 24780 | G59: 12600 | H59: =+F59-G59 -> 12180 | I59: 2 | J59: =+H59-H59*I59/100 -> 11936.4 | K59: 3650 | L59: =+J59*K59 -> 43567860 | P59: 41848000 | Q59: =+L59-P59 -> 1719860
C60: =199*3650 -> 726350 | D60: 642 199 кг | E60: 368 мяхк бобир | F60: 24280 | G60: 12580 | H60: =+F60-G60 -> 11700 | I60: 2 | J60: =+H60-H60*I60/100 -> 11466 | K60: 3650 | L60: =+J60*K60 -> 41850900 | P60: 40950000 | Q60: =+L60-P60 -> 900900
C61: =248*3650 -> 905200 | D61: 074 248 кг | E61: 886 мяхки жамил | F61: 27680 | G61: 13300 | H61: =+F61-G61 -> 14380 | I61: 2 | J61: =+H61-H61*I61/100 -> 14092.4 | K61: 3650 | L61: =+J61*K61 -> 51437260 | P61: 50225000 | Q61: =+L61-P61 -> 1212260
C62: =512*3650 -> 1868800 | D62: 384 512 кг | E62: 266 мяхки ислом | F62: 26680 | G62: 12180 | H62: =+F62-G62 -> 14500 | I62: 2 | J62: =+H62-H62*I62/100 -> 14210 | K62: 3900 | L62: =+J62*K62 -> 55419000 | P62: 53410000 | Q62: =+L62-P62 -> 2009000
C63: =1040*3650 -> 3796000 | D63: 996 1040 кг | E63: 264 мяхк тур | F63: 21080 | G63: 10850 | H63: =+F63-G63 -> 10230 | I63: 2 | J63: =+H63-H63*I63/100 -> 10025.4 | K63: 3650 | L63: =+J63*K63 -> 36592710 | P63: 35723000 | Q63: =+L63-P63 -> 869710
H64: =+F64-G64 -> 0 | J64: =+H64-H64*I64/100 -> 0 | L64: =+J64*K64 -> 0 | Q64: =+L64-P64 -> 0
H65: =+F65-G65 -> 0 | J65: =+H65-H65*I65/100 -> 0 | L65: =+J65*K65 -> 0 | Q65: =+L65-P65 -> 0
A66: 14,02,2026 | C66: =20000*12230 -> 244600000 | D66: 20,000 $ | E66: 377 мяхки пешку | F66: 17320 | G66: 9400 | H66: =+F66-G66 -> 7920 | I66: 2 | J66: =+H66-H66*I66/100 -> 7761.6 | K66: 3650 | L66: =+J66*K66 -> 28329840 | P66: 27650000 | Q66: =+L66-P66 -> 679840
E67: 215 мяхк нодир | F67: 32120 | G67: 16120 | H67: =+F67-G67 -> 16000 | I67: 2 | J67: =+H67-H67*I67/100 -> 15680 | K67: 3650 | L67: =+J67*K67 -> 57232000 | P67: 55400000 | Q67: =+L67-P67 -> 1832000
E68: 999 мяхки нодир нов | F68: 24070 | G68: 10830 | H68: =+F68-G68 -> 13240 | I68: 1.5 | J68: =+H68-H68*I68/100 -> 13041.4 | K68: 3650 | L68: =+J68*K68 -> 47601110 | P68: =3850*12250 -> 47162500 | Q68: =+L68-P68 -> 438610
E69: 413 турон | F69: 28110 | G69: 14850 | H69: =+F69-G69 -> 13260 | I69: 2 | J69: =+H69-H69*I69/100 -> 12994.8 | K69: 3650 | L69: =+J69*K69 -> 47431020 | P69: 46017000 | Q69: =+L69-P69 -> 1414020
E70: 698 бекобод ислом | F70: 9920 | G70: 5060 | H70: =+F70-G70 -> 4860 | I70: 4.4 | J70: =+H70-H70*I70/100 -> 4646.16 | K70: 3600 | L70: =+J70*K70 -> 16726176 | P70: 16493000 | Q70: =+L70-P70 -> 233176
C71: =3500*12230 -> 42805000 | D71: 3500 $ | E71: 574 бекобод | F71: 25020 | G71: 13160 | H71: =+F71-G71 -> 11860 | I71: 2 | J71: =+H71-H71*I71/100 -> 11622.8 | K71: 3350 | L71: =+J71*K71 -> 38936380 | P71: 38355000 | Q71: =+L71-P71 -> 581380
C72: =212*3650 -> 773800 | D72: 187 мош 212 кг | H72: =+F72-G72 -> 0 | J72: =+H72-H72*I72/100 -> 0 | L72: =+J72*K72 -> 0 | Q72: =+L72-P72 -> 0
A73: 15,02,2026 | C73: =20000*12230 -> 244600000 | D73: 20,000 $ | E73: 562 нодир мяхки | F73: 19030 | G73: 9780 | H73: =+F73-G73 -> 9250 | I73: 2 | J73: =+H73-H73*I73/100 -> 9065 | K73: 3650 | L73: =+J73*K73 -> 33087250 | P73: 32200000 | Q73: =+L73-P73 -> 887250
C74: 800000 | D74: 445 мошин | E74: 445 мошин | F74: 20430 | G74: 9350 | H74: =+F74-G74 -> 11080 | I74: 2.3 | J74: =+H74-H74*I74/100 -> 10825.16 | K74: 3650 | L74: =+J74*K74 -> 39511834 | P74: 37390000 | Q74: =+L74-P74 -> 2121834
C75: 450000 | D75: 384 мошин | E75: 384 бекобод | F75: 24660 | G75: 13340 | H75: =+F75-G75 -> 11320 | I75: 2.4 | J75: =+H75-H75*I75/100 -> 11048.32 | K75: 3350 | L75: =+J75*K75 -> 37011872 | P75: 36459000 | Q75: =+L75-P75 -> 552872
E76: 597 мяхки ром | F76: 22130 | G76: 11320 | H76: =+F76-G76 -> 10810 | I76: 3.8 | J76: =+H76-H76*I76/100 -> 10399.22 | K76: 3650 | L76: =+J76*K76 -> 37957153 | P76: 37907000 | Q76: =+L76-P76 -> 50153
C77: 6000000 | D77: 266 мошин | H77: =+F77-G77 -> 0 | J77: =+H77-H77*I77/100 -> 0 | L77: =+J77*K77 -> 0 | Q77: =+L77-P77 -> 0
C78: 1235000 | D78: 368 мошин | H78: =+F78-G78 -> 0 | J78: =+H78-H78*I78/100 -> 0 | L78: =+J78*K78 -> 0 | Q78: =+L78-P78 -> 0
C79: 1070000 | D79: 264 мошин | H79: =+F79-G79 -> 0 | J79: =+H79-H79*I79/100 -> 0 | L79: =+J79*K79 -> 0 | Q79: =+L79-P79 -> 0
A80: 16,02,2026 | B80: =750*12230 -> 9172500 | D80: 750 $ 30,000 $ | E80: 642 мяхки тур | F80: 25080 | G80: 12740 | H80: =+F80-G80 -> 12340 | I80: 2 | J80: =+H80-H80*I80/100 -> 12093.2 | K80: 3650 | L80: =+J80*K80 -> 44140180 | P80: 43100000 | Q80: =+L80-P80 -> 1040180
C81: 70000 | D81: 267 шофир | E81: 267 мяхки ислом | F81: 9920 | G81: 5020 | H81: =+F81-G81 -> 4900 | I81: 3.6 | J81: =+H81-H81*I81/100 -> 4723.6 | K81: 3550 | L81: =+J81*K81 -> 16768780 | P81: 16350000 | Q81: =+L81-P81 -> 418780
C82: 50000000 | D82: икром олди | E82: 872 мяяхк ислом | F82: 10120 | G82: 5150 | H82: =+F82-G82 -> 4970 | I82: 2 | J82: =+H82-H82*I82/100 -> 4870.6 | K82: 3900 | L82: =+J82*K82 -> 18995340 | P82: 18319000 | Q82: =+L82-P82 -> 676340
A83: 17,02,2026 | C83: =15000*12170 -> 182550000 | D83: 15,000 $ олдим | E83: 704 ислом мяхк | F83: 9800 | G83: 4550 | H83: =+F83-G83 -> 5250 | I83: 2 | J83: =+H83-H83*I83/100 -> 5145 | K83: 3900 | L83: =+J83*K83 -> 20065500 | P83: 19350000 | Q83: =+L83-P83 -> 715500
C84: =2000*12170 -> 24340000 | D84: 2000 $ ислом | E84: 187 мяхк турон | F84: 19950 | G84: 8980 | H84: =+F84-G84 -> 10970 | I84: 2 | J84: =+H84-H84*I84/100 -> 10750.6 | K84: 3650 | L84: =+J84*K84 -> 39239690 | P84: 38307000 | Q84: =+L84-P84 -> 932690
D85: 0 | E85: 215 лист нодир | F85: 29560 | G85: 16030 | H85: =+F85-G85 -> 13530 | I85: 1 | J85: =+H85-H85*I85/100 -> 13394.7 | K85: 3650 | L85: =+J85*K85 -> 48890655 | P85: 47335000 | Q85: =+L85-P85 -> 1555655
D86: 0 | H86: =+F86-G86 -> 0 | J86: =+H86-H86*I86/100 -> 0 | L86: =+J86*K86 -> 0 | Q86: =+L86-P86 -> 0
D87: 0 | H87: =+F87-G87 -> 0 | J87: =+H87-H87*I87/100 -> 0 | L87: =+J87*K87 -> 0 | Q87: =+L87-P87 -> 0
D88: 0 | H88: =+F88-G88 -> 0 | J88: =+H88-H88*I88/100 -> 0 | L88: =+J88*K88 -> 0 | Q88: =+L88-P88 -> 0
A89: 18,02,2026 | E89: 180 мяхки ислом | F89: 7320 | G89: 3740 | H89: =+F89-G89 -> 3580 | I89: 2 | J89: =+H89-H89*I89/100 -> 3508.4 | K89: 3900 | L89: =+J89*K89 -> 13682760 | P89: 13195000 | Q89: =+L89-P89 -> 487760
E90: 377 мяхки зур | F90: 19950 | G90: 9430 | H90: =+F90-G90 -> 10520 | J90: =+H90-H90*I90/100 -> 10520 | K90: 3650 | L90: =+J90*K90 -> 38398000 | P90: 37493000 | Q90: =+L90-P90 -> 905000
E91: 537 чугун жамил | F91: 20920 | G91: 10580 | H91: =+F91-G91 -> 10340 | I91: 5 | J91: =+H91-H91*I91/100 -> 9823 | K91: 3350 | L91: =+J91*K91 -> 32907050 | P91: 32415000 | Q91: =+L91-P91 -> 492050
E92: 574 чугун жамил | F92: 25700 | G92: 13200 | H92: =+F92-G92 -> 12500 | I92: 5 | J92: =+H92-H92*I92/100 -> 11875 | K92: 3350 | L92: =+J92*K92 -> 39781250 | P92: 39187000 | Q92: =+L92-P92 -> 594250
D93: 0 | H93: =+F93-G93 -> 0 | J93: =+H93-H93*I93/100 -> 0 | L93: =+J93*K93 -> 0 | Q93: =+L93-P93 -> 0
D94: 0 | H94: =+F94-G94 -> 0 | J94: =+H94-H94*I94/100 -> 0 | L94: =+J94*K94 -> 0 | Q94: =+L94-P94 -> 0
D95: 0 | H95: =+F95-G95 -> 0 | J95: =+H95-H95*I95/100 -> 0 | L95: =+J95*K95 -> 0 | Q95: =+L95-P95 -> 0
A96: 19,02,2026 | C96: =30000*12150 -> 364500000 | D96: 30,000 $ | E96: 413 мяхки т | F96: 27050 | G96: 14880 | H96: =+F96-G96 -> 12170 | I96: 2 | J96: =+H96-H96*I96/100 -> 11926.6 | K96: 3650 | L96: =+J96*K96 -> 43532090 | P96: 42500000 | Q96: =+L96-P96 -> 1032090
E97: 810 бекобод | F97: 24180 | G97: 13660 | H97: =+F97-G97 -> 10520 | I97: 2 | J97: =+H97-H97*I97/100 -> 10309.6 | K97: 3350 | L97: =+J97*K97 -> 34537160 | P97: 34016000 | Q97: =+L97-P97 -> 521160
C98: 600000 | D98: 704 мошин | H98: =+F98-G98 -> 0 | J98: =+H98-H98*I98/100 -> 0 | L98: =+J98*K98 -> 0 | Q98: =+L98-P98 -> 0
H99: =+F99-G99 -> 0 | J99: =+H99-H99*I99/100 -> 0 | L99: =+J99*K99 -> 0 | Q99: =+L99-P99 -> 0
A100: 20,02,2026 | C100: 250000 | D100: 445 ШОФИР | E100: 445 МЯХКИ ПЕШКУ Ф | F100: 20820 | G100: 9220 | H100: =+F100-G100 -> 11600 | I100: 2 | J100: =+H100-H100*I100/100 -> 11368 | K100: 3650 | L100: =+J100*K100 -> 41493200 | P100: 39741000 | Q100: =+L100-P100 -> 1752200
...

Sheet дафтарча
B2: Дата | C2: Сабаб | D2: Ойбек | E2: Мошин номер | F2: Брутто | G2: Нетто | H2: ТОНН | I2: Скидка | J2: Цена | K2: Феруз укаси
D3: =+SUM(D4:D46) -> 0 | H3: =+SUM(H4:H46) -> 4910 | K3: =+SUM(K4:K46) -> 17013150 | L3: Ойбек пул берди | M3: =+D3 -> 0
B4: 01,09,26 | E4: 919 | F4: 18800 | G4: 13890 | H4: =+F4-G4 -> 4910 | I4: 1 | J4: 3500 | K4: =+(H4-H4*I4/100)*J4 -> 17013150 | L4: =+K2 -> Феруз укаси | M4: =+K3 -> 17013150
H5: =+F5-G5 -> 0 | K5: =+(H5-H5*I5/100)*J5 -> 0 | L5: Делта | M5: =+M3-M4 -> -17013150
H6: =+F6-G6 -> 0 | K6: =+(H6-H6*I6/100)*J6 -> 0
H7: =+F7-G7 -> 0 | K7: =+(H7-H7*I7/100)*J7 -> 0
H8: =+F8-G8 -> 0 | K8: =+(H8-H8*I8/100)*J8 -> 0
H9: =+F9-G9 -> 0 | K9: =+(H9-H9*I9/100)*J9 -> 0
H10: =+F10-G10 -> 0 | K10: =+(H10-H10*I10/100)*J10 -> 0
H11: =+F11-G11 -> 0 | K11: =+(H11-H11*I11/100)*J11 -> 0
H12: =+F12-G12 -> 0 | K12: =+(H12-H12*I12/100)*J12 -> 0
H13: =+F13-G13 -> 0 | K13: =+(H13-H13*I13/100)*J13 -> 0
H14: =+F14-G14 -> 0 | K14: =+(H14-H14*I14/100)*J14 -> 0
H15: =+F15-G15 -> 0 | K15: =+(H15-H15*I15/100)*J15 -> 0
H16: =+F16-G16 -> 0 | K16: =+(H16-H16*I16/100)*J16 -> 0
H17: =+F17-G17 -> 0 | K17: =+(H17-H17*I17/100)*J17 -> 0
... H46: =+F46-G46 -> 0 | K46: =+(H46-H46*I46/100)*J46 -> 0
B57: Дата | C57: Сабаб | D57: Ойбек | E57: Мошин номер | F57: Брутто | G57: Нетто | H57: ТОНН | I57: Скидка | J57: Цена | K57: шамсилло
D58: =+SUM(D59:D107) -> 223288000 | H58: =+SUM(H59:H107) -> 60780 | K58: =+SUM(K59:K107) -> 211472295 | L58: Ойбек пул берди | M58: =+D58 -> 223288000
B59: 28,08,2026 | C59: 886 мош 190 кг | D59: =190*3200 -> 608000 | H59: =+F59-G59 -> 0 | K59: =+(H59-H59*I59/100)*J59 -> 0 | L59: =+K57 -> шамсилло | M59: =+K58 -> 211472295
B60: 28,08,2026 | C60: 4000 | D60: =4000*11825 -> 47300000 | H60: =+F60-G60 -> 0 | K60: =+(H60-H60*I60/100)*J60 -> 0 | L60: Делта | M60: =+M58-M59 -> 11815705
B61: 29,08,2026 | C61: 5000 | D61: =5000*11850 -> 59250000 | E61: 467 | F61: 22310 | G61: 12990 | H61: =+F61-G61 -> 9320 | I61: 0.5 | J61: 3750 | K61: =+(H61-H61*I61/100)*J61 -> 34775250
E62: 834 | F62: 24090 | G62: 12580 | H62: =+F62-G62 -> 11510 | I62: 3 | J62: 3600 | K62: =+(H62-H62*I62/100)*J62 -> 40192920
B63: 30,08,2026 | E63: 576 | F63: 13040 | G63: 9310 | H63: =+F63-G63 -> 3730 | I63: 1 | J63: 3750 | K63: =+(H63-H63*I63/100)*J63 -> 13847625
B64: 31,08,2026 | C64: 3800 | D64: =3800*11850 -> 45030000 | E64: 886 | F64: 26040 | G64: 12900 | H64: =+F64-G64 -> 13140 | I64: 3 | J64: 3300 | K64: =+(H64-H64*I64/100)*J64 -> 42061140
E65: 773 | F65: 28730 | G65: 14730 | H65: =+F65-G65 -> 14000 | I65: 3 | J65: 3600 | K65: =+(H65-H65*I65/100)*J65 -> 48888000
E66: 267 | F66: 17450 | G66: 8370 | H66: =+F66-G66 -> 9080 | I66: 3 | J66: 3600 | K66: =+(H66-H66*I66/100)*J66 -> 31707360
B67: 01,09,26 | C67: 6000 | D67: =6000*11850 -> 71100000 | H67: =+F67-G67 -> 0 | K67: =+(H67-H67*I67/100)*J67 -> 0
H68: =+F68-G68 -> 0 | K68: =+(H68-H68*I68/100)*J68 -> 0
H69: =+F69-G69 -> 0 | K69: =+(H69-H69*I69/100)*J69 -> 0
H70: =+F70-G70 -> 0 | K70: =+(H70-H70*I70/100)*J70 -> 0
H71: =+F71-G71 -> 0 | K71: =+(H71-H71*I71/100)*J71 -> 0
H72: =+F72-G72 -> 0 | K72: =+(H72-H72*I72/100)*J72 -> 0
H73: =+F73-G73 -> 0 | K73: =+(H73-H73*I73/100)*J73 -> 0
H74: =+F74-G74 -> 0 | K74: =+(H74-H74*I74/100)*J74 -> 0
H75: =+F75-G75 -> 0 | K75: =+(H75-H75*I75/100)*J75 -> 0
H76: =+F76-G76 -> 0 | K76: =+(H76-H76*I76/100)*J76 -> 0
H77: =+F77-G77 -> 0 | K77: =+(H77-H77*I77/100)*J77 -> 0
H78: =+F78-G78 -> 0 | K78: =+(H78-H78*I78/100)*J78 -> 0
H79: =+F79-G79 -> 0 | K79: =+(H79-H79*I79/100)*J79 -> 0
... H107: =+F107-G107 -> 0 | K107: =+(H107-H107*I107/100)*J107 -> 0
B110: дата | C110: Сабаб | D110: Ойбек | E110: Мошин номер | F110: Брутто | G110: Нетто | H110: ТОНН | I110: Скидка | J110: Цена | K110: сает
D111: =+SUM(D112:D130) -> 10000000 | H111: =+SUM(H112:H130) -> 0 | K111: =+SUM(K112:K130) -> 0 | L111: Ойбек пул берди | M111: =+D111 -> 10000000
B112: 27,08,2026 | C112: 844 | D112: 10000000 | H112: =+F112-G112 -> 0 | K112: =+(H112-H112*I112/100)*J112 -> 0 | L112: =+K110 -> сает | M112: =+K111 -> 0
H113: =+F113-G113 -> 0 | K113: =+(H113-H113*I113/100)*J113 -> 0 | L113: Делта | M113: =+M111-M112 -> 10000000
H114: =+F114-G114 -> 0 | K114: =+(H114-H114*I114/100)*J114 -> 0
H115: =+F115-G115 -> 0 | K115: =+(H115-H115*I115/100)*J115 -> 0
H116: =+F116-G116 -> 0 | K116: =+(H116-H116*I116/100)*J116 -> 0
H117: =+F117-G117 -> 0 | K117: =+(H117-H117*I117/100)*J117 -> 0
H118: =+F118-G118 -> 0 | K118: =+(H118-H118*I118/100)*J118 -> 0
H119: =+F119-G119 -> 0 | K119: =+(H119-H119*I119/100)*J119 -> 0
H120: =+F120-G120 -> 0 | K120: =+(H120-H120*I120/100)*J120 -> 0
H121: =+F121-G121 -> 0 | K121: =+(H121-H121*I121/100)*J121 -> 0
H122: =+F122-G122 -> 0 | K122: =+(H122-H122*I122/100)*J122 -> 0
H123: =+F123-G123 -> 0 | K123: =+(H123-H123*I123/100)*J123 -> 0
H124: =+F124-G124 -> 0 | K124: =+(H124-H124*I124/100)*J124 -> 0
H125: =+F125-G125 -> 0 | K125: =+(H125-H125*I125/100)*J125 -> 0
... H130: =+F130-G130 -> 0 | K130: =+(H130-H130*I130/100)*J130 -> 0
B134: Дата | C134: Сабаб | D134: Ойбек | E134: Мошин номер | F134: Брутто | G134: Нетто | H134: ТОНН | I134: Скидка | J134: Цена | K134: хасан
D135: =+SUM(D136:D145) -> 56734000 | H135: =+SUM(H136:H152) -> 6950 | K135: =+SUM(K136:K152) -> 37382500 | L135: Ойбек пул берди | M135: =+D135 -> 56734000
B136: 5,07,2026 | C136: 500 $ | D136: 6000000 | H136: =+F136-G136 -> 0 | K136: =+(H136-H136*I136/100)*J136 -> 0 | L136: =+K134 -> хасан | M136: =+K135 -> 37382500
B137: 1,08,2026 | C137: 500 $ | D137: 6015000 | H137: =+F137-G137 -> 0 | K137: 9330000 | L137: Делта | M137: =+M135-M136 -> 19351500
H138: =+F138-G138 -> 0 | K138: 2685000
B139: 2,08,2026 | C139: сум | D139: 10000000 | H139: =+F139-G139 -> 0 | K139: =+(H139-H139*I139/100)*J139 -> 0
B140: 3,08,2026 | H140: 2230 | J140: 3650 | K140: =+(H140-H140*I140/100)*J140 -> 8139500
H141: 4720 | J141: 3650 | K141: =+(H141-H141*I141/100)*J141 -> 17228000
B142: 4,08,2026 | C142: 1900 $ | D142: =1900*12010 -> 22819000 | H142: =+F142-G142 -> 0 | K142: =+(H142-H142*I142/100)*J142 -> 0
B143: 6,08,2026 | H143: =+F143-G143 -> 0 | K143: =+(H143-H143*I143/100)*J143 -> 0
B144: 17,08,2026 | C144: 1000 $ | D144: 11900000 | H144: =+F144-G144 -> 0 | K144: =+(H144-H144*I144/100)*J144 -> 0
H145: =+F145-G145 -> 0 | K145: =+(H145-H145*I145/100)*J145 -> 0
H146: =+F146-G146 -> 0 | K146: =+(H146-H146*I146/100)*J146 -> 0
H147: =+F147-G147 -> 0 | K147: =+(H147-H147*I147/100)*J147 -> 0
H148: =+F148-G148 -> 0 | K148: =+(H148-H148*I148/100)*J148 -> 0
H149: =+F149-G149 -> 0 | K149: =+(H149-H149*I149/100)*J149 -> 0
H150: =+F150-G150 -> 0 | K150: =+(H150-H150*I150/100)*J150 -> 0
H151: =+F151-G151 -> 0 | K151: =+(H151-H151*I151/100)*J151 -> 0
H152: =+F152-G152 -> 0 | K152: =+(H152-H152*I152/100)*J152 -> 0
B155: Дата | C155: Сабаб | D155: Ойбек | E155: Мошин номер | F155: Брутто | G155: Нетто | H155: ТОНН | I155: Скидка | J155: Цена | K155: мехри вобкент
D156: =+SUM(D157:D166) -> 26605000 | H156: =+SUM(H157:H166) -> 8765 | K156: =+SUM(K157:K166) -> 30070750 | L156: Ойбек пул берди | M156: =+D156 -> 26605000
B157: 23,07,2026 | C157: 700 $ | D157: =700*12100 -> 8470000 | H157: =+F157-G157 -> 0 | K157: =+(H157-H157*I157/100)*J157 -> 0 | L157: =+K155 -> мехри вобкент | M157: =+K156 -> 30070750
B158: 24,07,2026 | C158: 1500 $ | D158: =1500*12090 -> 18135000 | H158: 6020 | J158: 3650 | K158: =+(H158-H158*I158/100)*J158 -> 21973000 | L158: Делта | M158: =+M156-M157 -> -3465750
B159: 28,07,2026 | H159: 2745 | J159: 2950 | K159: =+(H159-H159*I159/100)*J159 -> 8097750
H160: =+F160-G160 -> 0 | K160: =+(H160-H160*I160/100)*J160 -> 0
H161: =+F161-G161 -> 0 | K161: =+(H161-H161*I161/100)*J161 -> 0
H162: =+F162-G162 -> 0 | K162: =+(H162-H162*I162/100)*J162 -> 0
H163: =+F163-G163 -> 0 | K163: =+(H163-H163*I163/100)*J163 -> 0
H164: =+F164-G164 -> 0 | K164: =+(H164-H164*I164/100)*J164 -> 0
H165: =+F165-G165 -> 0 | K165: =+(H165-H165*I165/100)*J165 -> 0
H166: =+F166-G166 -> 0 | K166: =+(H166-H166*I166/100)*J166 -> 0
B169: ё | C169: Сабаб | D169: Ойбек | E169: Мошин номер | F169: Брутто | G169: Нетто | H169: ТОНН | I169: Скидка | J169: Цена | K169: мавлон
D170: =+SUM(D171:D180) -> 17775000 | H170: =+SUM(H171:H180) -> 11460 | K170: =+SUM(K171:K180) -> 41765970 | L170: Ойбек пул берди | M170: =+D170 -> 17775000
B171: 30,08,2026 | C171: 1500 | D171: =1500*11850 -> 17775000 | E171: 576 | F171: 24510 | G171: 13050 | H171: =+F171-G171 -> 11460 | I171: 1.5 | J171: 3700 | K171: =+(H171-H171*I171/100)*J171 -> 41765970 | L171: =+K169 -> мавлон | M171: =+K170 -> 41765970
H172: =+F172-G172 -> 0 | K172: =+(H172-H172*I172/100)*J172 -> 0 | L172: Делта | M172: =+M170-M171 -> -23990970
H173: =+F173-G173 -> 0 | K173: =+(H173-H173*I173/100)*J173 -> 0
H174: =+F174-G174 -> 0 | K174: =+(H174-H174*I174/100)*J174 -> 0
H175: =+F175-G175 -> 0 | K175: =+(H175-H175*I175/100)*J175 -> 0
H176: =+F176-G176 -> 0 | K176: =+(H176-H176*I176/100)*J176 -> 0
H177: =+F177-G177 -> 0 | K177: =+(H177-H177*I177/100)*J177 -> 0
H178: =+F178-G178 -> 0 | K178: =+(H178-H178*I178/100)*J178 -> 0
H179: =+F179-G179 -> 0 | K179: =+(H179-H179*I179/100)*J179 -> 0
...

Sheet Кунлик
A1: № | C1: $ | D1: А ман карз | E1: Ман Карз
D2: =+SUM(D5:D10037) -> 301869165 | E2: =+SUM(E5:E10037) -> 1.2599641e+09 | F2: Кунлик | G2: =D2-E2 -> -9.5809495e+08
F3: Приход-расход | G3: =+'Приход-Расход'!C2 -> -9.5809495e+08
F4: Делта | G4: =+G2-G3 -> 2.1457672e-06
A5: 1 | B5: Ойбек - Тура ака | E5: =+'тура ака'!N3 -> -1.1849354e+09
A6: =+A5+1 -> 2 | B6: Хитой | E6: =+Хитой!C38 -> 0 | F6: Корхоно | G6: =+Каракул!D56*-1 -> -141473600
A7: =+A6+1 -> 3 | B7: Хитой фойда | E7: =+Хитой!C41 -> 0 | F7: Итого уйиндан карз | G7: =+G6+G3+17010000 -> -1.0825585e+09 | H7: =+G7/12000 -> -90213.212
A8: =+A7+1 -> 4 | B8: Нурбек кунлик | E8: =+Хитой!C48 -> 0 | F8: Гостиница | G8: =+Гостиница!C3 -> 0
A9: =+A8+1 -> 5 | B9: Раим Пул | D9: =+Рахим!B18 -> 72520000
A10: =+A9+1 -> 6 | B10: Раим товар | D10: =Рахим!B19 -> 37320000 | E10: =+Рахим!B17 -> 3439500 | F10: Утган ой да карз | G10: 1082558547
A11: =+A10+1 -> 7 | B11: Чермет бонус | E11: =+'Чермт Бонус'!H4 -> 0 | F11: Делта | G11: =+G10+G7 -> 0.42600036
A12: =+A11+1 -> 8 | B12: Иззат | D12: =+Рахим!M2 -> 101446000 | F12: Итого | G12: =+G8+G11 -> 0.42600036
A13: =+A12+1 -> 9 | B13: =+Рахим!T1 -> рахим киленти янги | D13: =+Рахим!R2 -> 0
A14: =+A13+1 -> 10 | B14: наим тогом | D14: =+тогом!A2 -> -14976200
A15: =+A14+1 -> 11 | B15: =+тонн!I1 -> Остатка Нурбек | D15: =+тонн!I2 -> 77200000
A16: 10 | B16: =+дафтарча!K2 -> Феруз укаси | D16: =+дафтарча!M5 -> -17013150
A17: =+A16+1 -> 11 | B17: =+Бонусча!G2 -> Хитой бонусча | D17: =+Бонусча!I7 -> 0
A18: =+A17+1 -> 12 | B18: =+дафтарча!K57 -> шамсилло | D18: =+дафтарча!M60 -> 11815705
A19: =+A18+1 -> 13 | B19: =+дафтарча!K110 -> сает | D19: =+дафтарча!M113 -> 10000000
A20: =+A19+1 -> 14 | B20: =+дафтарча!K134 -> хасан | D20: =+дафтарча!M137 -> 19351500 | F20: Кунлик | G20: =+SUM(D16:D68) -> -157740135
A21: =+A20+1 -> 15 | B21: =+дафтарча!K155 -> мехри вобкент | D21: =+дафтарча!M158 -> -3465750 | F21: Дафтарча | G21: =+дафтарча!P4+Бонусча!I7 -> 0
A22: =+A21+1 -> 16 | B22: =+дафтарча!K169 -> мавлон | D22: =+дафтарча!M172 -> -23990970 | F22: Делта | G22: =+G20-G21 -> -157740135
A23: =+A22+1 -> 17 | B23: =+дафтарча!K185 -> бобир того | D23: =+дафтарча!M188 -> -26935550
A24: =+A23+1 -> 18 | B24: =+дафтарча!K204 -> сироч ака 20 тн | D24: =+дафтарча!M207 -> -60000000
A25: =+A24+1 -> 19 | B25: =+дафтарча!K218 -> САРДОР | D25: =+дафтарча!M221 -> -254600
A26: =+A25+1 -> 20 | B26: =+дафтарча!K247 -> али, | D26: =+дафтарча!M250 -> 14280000
A27: =+A26+1 -> 21 | B27: =+дафтарча!K265 -> одил ака | D27: =+дафтарча!M268 -> 2825000
A28: =+A27+1 -> 22 | B28: =+дафтарча!K277 -> фармон | D28: =+дафтарча!M280 -> 8130000
A29: =+A28+1 -> 23 | B29: =+дафтарча!K294 -> Достон пешку | D29: =+дафтарча!M297 -> -33340000
A30: =+A29+1 -> 24 | B30: =+дафтарча!K321 -> истат | D30: =+дафтарча!M324 -> -42537320
A31: =+A30+1 -> 25 | B31: =+дафтарча!K338 -> сироч еко | D31: =+дафтарча!M341 -> -20160000
A32: =+A31+1 -> 26 | B32: =+дафтарча!K378 -> запас | D32: =+дафтарча!M381 -> 0
A33: =+A32+1 -> 27 | B33: =+дафтарча!K392 -> запас | D33: =+дафтарча!M395 -> 0
A34: =+A33+1 -> 28 | B34: =+дафтарча!K406 -> запас | D34: =+дафтарча!M409 -> 0
A35: =+A34+1 -> 29 | B35: =+дафтарча!K427 -> запас | D35: =+дафтарча!M430 -> 0
A36: =+A35+1 -> 30 | B36: =+дафтарча!K441 -> запас | D36: =+дафтарча!M444 -> 0
A37: =+A36+1 -> 31 | B37: =+дафтарча!K455 -> запас | D37: =+дафтарча!M458 -> 0
A38: =+A37+1 -> 32 | B38: =+дафтарча!K469 -> запас | D38: =+дафтарча!M472 -> 0
A39: =+A38+1 -> 33 | B39: =+дафтарча!K493 -> запас | D39: =+дафтарча!M496 -> 0
A40: =+A39+1 -> 34 | B40: =+дафтарча!K506 -> запас | D40: =+дафтарча!M509 -> 0
A41: =+A40+1 -> 35 | B41: =+дафтарча!K519 -> запас | D41: =+дафтарча!M522 -> 0
A42: =+A41+1 -> 36 | B42: =+дафтарча!K532 -> запас | D42: =+дафтарча!M535 -> 0
A43: =+A42+1 -> 37 | B43: =+дафтарча!K545 -> запас | D43: =+дафтарча!M548 -> 0
A44: =+A43+1 -> 38 | B44: =+дафтарча!K558 -> запас | D44: =+дафтарча!M561 -> 0
A45: =+A44+1 -> 39 | B45: =+дафтарча!K571 -> запас | D45: =+дафтарча!M574 -> 0
A46: =+A45+1 -> 40 | B46: =+дафтарча!K584 -> запас | D46: =+дафтарча!M587 -> 0
A47: =+A46+1 -> 41 | B47: =+дафтарча!K603 -> запас | D47: =+дафтарча!M606 -> 0
A48: =+A47+1 -> 42 | B48: =+дафтарча!K352 -> фарход путури | D48: =+дафтарча!M355 -> 3555000
A49: =+A48+1 -> 43 | B49: =+дафтарча!K365 -> запас | D49: =+дафтарча!M368 -> 0
A50: =+A49+1 -> 44 | B50: =+дафтарча!K624 -> запас | D50: =+дафтарча!M627 -> 0
A51: =+A50+1 -> 45 | B51: =+дафтарча!K637 -> запас | D51: =+дафтарча!M640 -> 0
A52: =+A51+1 -> 46 | B52: =+дафтарча!K650 -> запас | D52: =+дафтарча!M653 -> 0
A53: =+A52+1 -> 47 | B53: =+дафтарча!K663 -> запас | D53: =+дафтарча!M666 -> 0
A54: =+A53+1 -> 48 | B54: =+дафтарча!K676 -> запас | D54: =+дафтарча!M679 -> 0
A55: =+A54+1 -> 49 | B55: =+дафтарча!K689 -> запас | D55: =+дафтарча!M692 -> 0
A56: =+A55+1 -> 50 | B56: =+дафтарча!K702 -> запас | D56: =+дафтарча!M705 -> 0
A57: =+A56+1 -> 51 | B57: =+дафтарча!K715 -> запас | D57: =+дафтарча!M718 -> 0
A58: =+A57+1 -> 52 | B58: =+дафтарча!K728 -> запас | D58: =+дафтарча!M731 -> 0
A59: =+A58+1 -> 53 | B59: =+дафтарча!K741 -> запас | D59: =+дафтарча!M744 -> 0
A60: =+A59+1 -> 54 | B60: =+дафтарча!K754 -> запас | D60: =+дафтарча!M757 -> 0
A61: =+A60+1 -> 55 | B61: =+дафтарча!K767 -> запас | D61: =+дафтарча!M770 -> 0
A62: =+A61+1 -> 56 | B62: =+дафтарча!K780 -> запас | D62: =+дафтарча!M783 -> 0
A63: =+A62+1 -> 57 | B63: =+дафтарча!K793 -> запас | D63: =+дафтарча!M796 -> 0
A64: =+A63+1 -> 58 | B64: =+дафтарча!K806 -> запас | D64: =+дафтарча!M809 -> 0
A65: =+A64+1 -> 59 | B65: =+дафтарча!K819 -> ЗАПАС | D65: =+дафтарча!M822 -> 0
A66: =+A65+1 -> 60 | B66: =+дафтарча!K832 -> запас | D66: =+дафтарча!M835 -> 0
A67: =+A66+1 -> 61 | B67: =+дафтарча!K845 -> запас | D67: =+дафтарча!M848 -> 0
A68: =+A67+1 -> 62 | B68: =+дафтарча!K858 -> запас | D68: =+дафтарча!M861 -> 0
A69: =+A68+1 -> 63 | B69: Чугун | E69: =+Чугун!P29 -> 0
A70: =+A69+1 -> 64 | B70: =+Чугун!N2 -> Навои Металл | E70: =+Чугун!D22 -> 0
A71: =+A70+1 -> 65 | B71: =+Чугун!C19 -> Рахим НАВОИ | D71: =+Чугун!D19 -> 0
A72: =+A71+1 -> 66 | B72: ИКРОМ | D72: 56900000
A73: =+A72+1 -> 67 | B73: чермет | D73: =7018*3000 -> 21054000
A74: =+A73+1 -> 68 | B74: ойбек доллор | C74: 1610 $ | D74: =1610*11850 -> 19078500
A75: =+A74+1 -> 69 | B75: ойбек пули кунлик | D75: 8400000
A76: =+A75+1 -> 70 | B76: пластик | D76: 5900000
A77: =+A76+1 -> 71 | B77: Фарход | D77: 1482000
A78: =+A77+1 -> 72 | B78: яхе | D78: 2000000
A79: =+A78+1 -> 73 | B79: 620 | C79: 220 кг | D79: =220*3000 -> 660000
A80: =+A79+1 -> 74 | B80: маймун | C80: 700 $ | D80: 8400000
A81: =+A80+1 -> 75 | B81: отамурод | D81: 95000
A82: =+A81+1 -> 76 | B82: неги 200 кг | D82: 700000
A83: =+A82+1 -> 77
A84: =+A83+1 -> 78
A85: =+A84+1 -> 79
A86: =+A85+1 -> 80
A87: =+A86+1 -> 81
A88: =+A87+1 -> 82
A89: =+A88+1 -> 83
A90: =+A89+1 -> 84
A91: =+A90+1 -> 85
A92: =+A91+1 -> 86
A93: =+A92+1 -> 87
A94: =+A93+1 -> 88
A95: =+A94+1 -> 89
A96: =+A95+1 -> 90 | F96: наги
A97: =+A96+1 -> 91 | F97: 1800 $
A98: =+A97+1 -> 92 | F98: 2700 $
A99: =+A98+1 -> 93 | B99: хотин 19+18+9+18=64 | C99: 64-4=60$ | E99: 50000000 | F99: 1900$
A100: =+A99+1 -> 94 | F100: 6400 $ карз
...

Sheet Приход-Расход
A1: Дата | B1: Расход сумма | C1: Расход Наименование | D1: Дата | E1: Приход сумма | F1: Приход Наименование
C2: =+E3-B3 -> -9.5809495e+08 | D2: =+C2/12150 -> -78855.551 | G2: Расход | H2: =+B3 -> 2905398055 | I2: 87,280 $
B3: =+SUM(B4:B9995) -> 2905398055 | C3: 342442112 | E3: =+SUM(E4:E9995) -> 1.9473031e+09 | G3: Делта | H3: =+#REF!-H2 -> #REF!
A4: 46053 | B4: 342442112 | C4: Йил бошида карзим | E4: 89000000 | F4: тилло
B5: 955000 | C5: зарар 834 | E5: 3000000 | F5: пр
B6: 1270000 | C6: жамил | E6: 2100000 | F6: чермет
B7: =1250*12150 -> 15187500 | C7: хура | E7: 38900000 | F7: хитой
B8: =1200*12150 -> 14580000 | C8: рахим | E8: 1700000 | F8: 004 турон
B9: 200000 | C9: бобо | E9: 1300000 | F9: 966 навои
B10: 200000 | C10: уйга бозор | E10: 6000000 | F10: рахим
B11: 200000 | C11: икром с | E11: 1035360 | F11: шунчаки
B12: 2500000 | C12: олим к
B13: 1000000 | C13: усто ужин
A14: 2,02,2026 | B14: 12000000 | C14: дадем | E14: =63570*50 -> 3178500 | F14: 142,388,130 релс
B15: 1400000 | C15: фарход | E15: 900000 | F15: 264 нов
B16: 1205655 | C16: 266 зарар | E16: 800000 | F16: чермет
A17: 3,02,2026 | B17: 500000 | C17: наги | E17: 400000 | F17: 884 жамил
B18: 900000 | C18: гастинса | E18: =5000*2900 -> 14500000 | F18: сироч ака
B19: 700000 | C19: 966 зарар | E19: 1400000 | F19: 365 чугун
B20: =321604+88500 -> 410104 | C20: акумлатр | E20: 800000 | F20: 377 бозорбой
B21: 1000000 | C21: доллор | E21: 900000 | F21: 904 ислом
B22: 2400000 | C22: 011 зарар | E22: =5000*250 -> 1250000 | F22: дакумент 5 тн
E23: =8244*100 -> 824400 | F23: исмат
A24: 4,03,2026 | B24: 150000 | C24: мойка | E24: 800000 | F24: ислом 725
B25: 800000 | C25: бозор | E25: 1400000 | F25: низом 074
B26: 200000 | C26: абед | E26: 3500000 | F26: низом газли 445
B27: 750000 | C27: бек апа | E27: 400000 | F27: бобир 574
B28: 400000 | C28: клик тахи | E28: 800000 | F28: бобир 463
B29: 190000 | C29: матерал | E29: 620000 | F29: комил 593
B30: =272671+224905 -> 497576 | C30: сироч 10 тн | E30: 1900000 | F30: турон 597
E31: 502111 | F31: фарод 413
E32: 1880000 | F32: 588 кг
A33: 5,02,2026 | B33: 300000 | C33: газ | E33: 600000 | F33: жора
B34: 100000 | C34: сартарош | E34: 900000 | F34: клик
B35: 100000 | C35: меличи | E35: 700000 | F35: 145 олот
B36: =1320*12250 -> 16170000 | C36: акфачи баня | E36: 600000 | F36: 437 олот
B37: 12200000 | C37: кадастр | E37: 2900000 | F37: 562 ром
E38: 400000 | F38: 032 еко
A39: 6,02,2026 | B39: =7541*3000 -> 22623000 | C39: каракул | E39: =+'тура ака'!Q28 -> 1147490 | F39: =+'тура ака'!E28 -> 996 ТУР МЯХКИ
B40: 100000 | C40: дори | E40: =+'тура ака'!Q29 -> 661538 | F40: =+'тура ака'!E29 -> 384 бекобод
B41: 400000 | C41: уборка | E41: =+'тура ака'!Q30 -> 896340 | F41: =+'тура ака'!E30 -> 537 мяхки комил
B42: 200000 | C42: реклама | E42: =+'тура ака'!Q31 -> 1022580 | F42: =+'тура ака'!E31 -> 377 мяхки рометан
B43: 200000 | C43: обед | E43: =+'тура ака'!Q32 -> 2009150 | F43: =+'тура ака'!E32 -> 714 бекобод жамил
B44: 200000 | C44: Бозор | E44: 1800000 | F44: Чермет бонус
B45: =228*2900 -> 661200 | C45: иззат | E45: =5000*2900 -> 14500000 | F45: сирож 5 тонн
B46: 200000 | C46: Алишер | E46: =+'тура ака'!Q35 -> 850700 | F46: =+'тура ака'!E35 -> 999 бекобод жамил
B47: =100*12200 -> 1220000 | C47: сирож | E47: =+'тура ака'!Q36 -> 835080 | F47: =+'тура ака'!E36 -> 698 мяхк ислом
B48: 777011 | C48: фарход кунлик | E48: 1 | F48: =+'тура ака'!E37 -> 0
B49: 1267000 | C49: 074 зарар | E49: 1 | F49: =+'тура ака'!E38 -> 0
B50: 858000 | C50: 445 зарар | E50: 1600000 | F50: чермет
A51: ,7,02,2026 | B51: 4000000 | C51: 4 тамошин | E51: =+'тура ака'!Q40 -> 0 | F51: =+'тура ака'!E40 -> 0
B52: 400000 | C52: наги | E52: =+'тура ака'!Q41 -> 0 | F52: =+'тура ака'!E41 -> 0
B53: 300000 | C53: ужин | E53: =+'тура ака'!Q42 -> -1095250 | F53: =+'тура ака'!E42 -> 413 прес
B54: 300000 | C54: мусур | D54: 8,02,2026 | E54: =+'тура ака'!Q43 -> 2582120 | F54: =+'тура ака'!E43 -> 642 мяхк ром
B55: 100000 | C55: сомса | F55: =+'тура ака'!E44 -> 0
B56: 3660000 | C56: кадастр | E56: =+'тура ака'!Q45 -> 1139030 | F56: =+'тура ака'!E45 -> 264 мяхк шамс
B57: 4200000 | C57: мактаб пул | E57: =+'тура ака'!Q46 -> 721540 | F57: =+'тура ака'!E46 -> 057 пешку жамил
B58: 1000000 | C58: бозор | E58: 5500000 | F58: рахим
B59: 300000 | C59: газ | D59: 9,02,2026 | E59: =+'тура ака'!Q47 -> 1547240 | F59: =+'тура ака'!E47 -> 074 мяхки нов
B60: 737651 | C60: кочган пул | E60: =6000*250 -> 1500000 | F60: дакумент
A61: 9,02,2026 | B61: 940000 | C61: пластик | E61: =+'тура ака'!Q49 -> 913587.5 | F61: =+'тура ака'!E49 -> 445 чугун тур бекобод
B62: 500000 | C62: жамил | E62: =+'тура ака'!Q50 -> 937437.5 | F62: =+'тура ака'!E50 -> 188 чугун тур бекобод
B63: 300000 | C63: дори | E63: =+'тура ака'!Q51 -> 1958300 | F63: =+'тура ака'!E51 -> 384 мяхк когон
B64: 785000 | C64: ХАМСОЯЯЯЯЯЯЯЯЯЯЯЯЯЯ | E64: 15000000 | F64: СИРОЧ АКА
B65: 400000 | C65: БОЗОР | E65: 1800000 | F65: чермет
B66: 500000 | C66: ГАЗ | E66: 1000000 | F66: 35 ТН
B67: 200000 | C67: РАДАР | D67: 11,02,2026 | E67: =+'тура ака'!Q55 -> 750680 | F67: =+'тура ака'!E55 -> 532 тур мяхки
B68: 217360 | C68: СИРОЧ ФАРХОД | E68: =+'тура ака'!Q56 -> 2182230 | F68: =+'тура ака'!E56 -> 996 мяхк ой
A69: 11,02,2026 | B69: 9300000 | C69: мошин кридит | D69: 12,02,2026 | E69: =+'тура ака'!Q57 -> 1886760 | F69: =+'тура ака'!E57 -> 187 КОГОН МЯХИ
B70: 2450000 | C70: икром лоша | E70: =+'тура ака'!Q58 -> 1359575 | F70: =+'тура ака'!E58 -> 184 ЧУГУН НИЗОМ
B71: 200000 | C71: алишер | D71: 13,02,2026 | E71: =+'тура ака'!Q59 -> 1719860 | F71: =+'тура ака'!E59 -> 229 мяхки фармон
B72: 330000 | C72: ужин | E72: =+'тура ака'!Q60 -> 900900 | F72: =+'тура ака'!E60 -> 368 мяхк бобир
A73: 12,02,2026 | B73: 10000000 | C73: САНТЕХНИК | E73: =+'тура ака'!Q61 -> 1212260 | F73: =+'тура ака'!E61 -> 886 мяхки жамил
B74: 300000 | C74: БОЗОР | E74: =+'тура ака'!Q62 -> 2009000 | F74: =+'тура ака'!E62 -> 266 мяхки ислом
B75: 100000 | C75: АБЕД | E75: =+'тура ака'!Q63 -> 869710 | F75: =+'тура ака'!E63 -> 264 мяхк тур
A76: 13,02,2026 | B76: 3450000 | C76: клик кадастр | E76: 1400000 | F76: жамил 600 4 тн дак
B77: 4000000 | C77: фарход гастинса учун | E77: 9225236 | F77: топилмаган пул
B78: 6700000 | C78: зарар 4 та мошин | D78: 14,02,2026 | E78: =+'тура ака'!Q66 -> 679840 | F78: =+'тура ака'!E66 -> 377 мяхки пешку
B79: 600000 | C79: ехсон | E79: =+'тура ака'!Q67 -> 1832000 | F79: =+'тура ака'!E67 -> 215 мяхк нодир
A80: 14,02,2026 | B80: 1500000 | C80: бозор | E80: =+'тура ака'!Q68 -> 438610 | F80: =+'тура ака'!E68 -> 999 мяхки нодир нов
B81: 800000 | C81: Бозор | E81: =+'тура ака'!Q69 -> 1414020 | F81: =+'тура ака'!E69 -> 413 турон
B82: 200000 | C82: мойка | E82: =+'тура ака'!Q70 -> 233176 | F82: =+'тура ака'!E70 -> 698 бекобод ислом
B83: 100000 | C83: абед | E83: =+'тура ака'!Q71 -> 581380 | F83: =+'тура ака'!E71 -> 574 бекобод
B84: =773800+880 -> 774680 | C84: шунчаки | E84: 700000 | F84: чермет
A85: 15,02,2026 | B85: 1000000 | C85: пластик | D85: 15,02,2026 | E85: =+'тура ака'!Q73 -> 887250 | F85: =+'тура ака'!E73 -> 562 нодир мяхки
B86: 200000 | C86: мойка | E86: =+'тура ака'!Q74 -> 2121834 | F86: =+'тура ака'!E74 -> 445 мошин
B87: 200000 | C87: бозор | E87: =+'тура ака'!Q75 -> 552872 | F87: =+'тура ака'!E75 -> 384 бекобод
A88: 16,02,2026 | B88: 3660000 | C88: шамшод | E88: =+'тура ака'!Q76 -> 50153 | F88: =+'тура ака'!E76 -> 597 мяхки ром
B89: 900000 | C89: мирик | E89: 1200000 | F89: хитой
B90: 1100000 | C90: наги | E90: 3600000 | F90: рахим
B91: 250000 | C91: 20 $ | E91: =+'тура ака'!Q79 -> 0 | F91: =+'тура ака'!E79 -> 0
B92: 400 газ | D92: 16,02,2026 | E92: =+'тура ака'!Q80 -> 1040180 | F92: =+'тура ака'!E80 -> 642 мяхки тур
A93: 17,02,2026 | B93: 400000 | C93: бобир | E93: =+'тура ака'!Q81 -> 418780 | F93: =+'тура ака'!E81 -> 267 мяхки ислом
B94: 700000 | C94: чермет 7 тн | E94: =+'тура ака'!Q82 -> 676340 | F94: =+'тура ака'!E82 -> 872 мяяхк ислом
B95: 1000000 | C95: картинка | D95: 17,02,2026 | E95: =+'тура ака'!Q83 -> 715500 | F95: =+'тура ака'!E83 -> 704 ислом мяхк
B96: 579314 | C96: зарар | E96: =+'тура ака'!Q84 -> 932690 | F96: =+'тура ака'!E84 -> 187 мяхк турон
A97: 18,02,2026 | B97: 12100000 | C97: илер жура | E97: =+'тура ака'!Q85 -> 1555655 | F97: =+'тура ака'!E85 -> 215 лист нодир
B98: 73200000 | C98: гастинса | E98: 1000000 | F98: 4 тн чермет
B99: 900000 | C99: бозор | E99: =1915*3000 -> 5745000 | F99: 1915 кг каракул
B100: 200000 | C100: алишер | E100: 800000 | F100: мехри
...

Sheet Чермт Бонус
A1: Дата | B1: Тонн | C1: Приход | D1: расход | E1: Нима учун | F1: Разница
C2: =+SUM(C5:C9214) -> 0 | D2: =+SUM(D5:D9214) -> 0 | F2: =+SUM(F5:F9214) -> 0 | G2: Приход | H2: =+C2 -> 0
G3: Расход | H3: =+D2 -> 0
G4: Фойда | H4: =+H2-H3-H7-H8-H9-H10-H11-H12 -> 0
A5: 46235 | C5: =+B5*100 -> 0 | G5: Ойбек | H5: =+H4/2 -> 0
A6: =+A5+1 -> 46236 | C6: =+B6*100 -> 0 | G6: Тура ака | H6: =+H5 -> 0
A7: =+A6+1 -> 46237 | C7: =+B7*100 -> 0 | G7: ИКРОМ
A8: =+A7+1 -> 46238 | C8: =+B8*100 -> 0 | G8: Алишер
A9: =+A8+1 -> 46239 | C9: =+B9*100 -> 0 | G9: мурод
A10: =+A9+1 -> 46240 | C10: =+B10*100 -> 0
A11: =+A10+1 -> 46241 | C11: =+B11*100 -> 0
A12: =+A11+1 -> 46242 | C12: =+B12*100 -> 0
A13: =+A12+1 -> 46243 | C13: =+B13*100 -> 0
A14: =+A13+1 -> 46244 | C14: =+B14*100 -> 0
A15: =+A14+1 -> 46245 | C15: =+B15*100 -> 0
A16: =+A15+1 -> 46246 | C16: =+B16*100 -> 0
A17: =+A16+1 -> 46247 | C17: =+B17*100 -> 0
A18: =+A17+1 -> 46248 | C18: =+B18*100 -> 0
A19: =+A18+1 -> 46249 | C19: =+B19*100 -> 0
A20: =+A19+1 -> 46250 | C20: =+B20*100 -> 0
A21: =+A20+1 -> 46251 | C21: =+B21*100 -> 0
... A35: =+A34+1 -> 46265 | C35: =+B35*100 -> 0

Sheet Рахим
A1: Дата | B1: Ойбек берган пул | C1: Раим Юк | D1: Харажат | E1: Мелоч харажат | F1: Сотилди | H1: Дата | I1: Рахим пули | J1: рахим расход | K1: САБАБ | M1: Дата | N1: Ойбек юк берди | O1: Иззат пул берди | P1: САБАБ | R1: Дата | S1: Ойбек юк берди | T1: рахим киленти янги | U1: САБАБ
A2: Утган хафтадан Колган пул | B2: =60340000+10200000 -> 70540000 | C2: 10200000 | H2: =I3-J3 -> 5639500 | M2: =N3-O3 -> 101446000 | R2: =S3-T3 -> 0
A3: душанба | B3: 41500000 | C3: 27120000 | D3: 2200000 | I3: =+SUM(I4:I9995) -> 27539500 | J3: =+SUM(J4:J18) -> 21900000 | N3: =+SUM(N4:N9995) -> 517803000 | O3: =+SUM(O4:O9995) -> 416357000 | S3: =+SUM(S4:S9995) -> 0 | T3: =+SUM(T4:T9995) -> 0
A4: Сешанба | H4: 10,08,2026 | I4: 10880000 | J4: 6600000 | M4: 18,08,2026 | N4: 48523000
A5: Чоршанба | H5: 18,08,2026 | I5: 3652500 | J5: 1000000 | K5: 48523000 | N5: 160995000 | O5: 50000000
A6: Пайшанба | O6: 60000000
A7: Жума | H7: 23,08,2026 | I7: 6622000 | J7: 6500000 | M7: 20,08,2026 | O7: 80000000
A8: Шанба | H8: 30,08,2026 | I8: 6385000 | J8: 7800000 | L8: - | M8: 23,08,2026 | N8: 172885000 | O8: 70000000
A9: Якшанба | M9: 26,08,2026 | O9: =2900*11830 -> 34307000 | P9: 2900*11830 $
O10: 15000000 | P10: сум
B11: =+SUM(B2:B10)-E11 -> 112040000 | C11: =+SUM(C2:C10) -> 37320000 | D11: =+SUM(D2:D10) -> 2200000 | E11: =+SUM(E2:E10) -> 0 | F11: =+SUM(F2:F10) -> 0 | M11: 30,08,2026 | N11: 135400000 | O11: 65550000 | P11: пул
M12: 31,08,2026 | O12: 41500000
A15: Харажат | B15: =+D11 -> 2200000 | C15: хафталик
A16: Раим пулаш | B16: 5639500 | C16: рахим пули шунга ез
A17: Раим пуаш Ойбекба | B17: =+B16-B15 -> 3439500
A18: Остаток | B18: =B11-C11-D11 -> 72520000
A19: Остатка юк | B19: =C11-F11 -> 37320000 | K19: 2900
A20: Фойда | B20: =+F11-C11 -> -37320000 | K20: 15
A21: Рахим фойда | B21: =+B20/2 -> -18660000

Sheet Каракул
A1: Дата | B1: Каракул Приход | C1: Каракул Расход | D1: БНПЗ | E1: Корхоно | F1: Тонн
E2: 24 01 2025 | F2: 380
A3: 10,04,2026 | B3: 594 | C3: 594 | E3: 13 02 2025 | F3: 104
E4: 19 02 2025 | F4: 107
E5: 14 04 2025 | F5: 349
E6: 16 04 2025 | F6: 300
E7: 18 04 2025 | F7: 286
E8: 10 06 2025 | F8: 78
E9: 1 07 2025 | F9: 570
E10: 2 07 2025 | F10: 310
E11: 19 07 2025 | F11: 407
E12: 19 07 2025 | F12: 95
E13: 21 08 2025 | F13: 105
E14: 2 09 2025 | F14: 280
E15: 3 09 2025 | F15: 7
... E21: 24 11 2025 | F21: 256
E22: 8689 кг
D25: 95
E28: 31,01,2026 СИРОЧ АКА | F28: 15000
E29: 3,02,2026 сироч ака | F29: 5000
E30: 06,02,2026 сирож ака | F30: 5000
E31: 10,02,2026 СИРОЧ АКА | F31: 5000
E32: 21,02,2026 сироч ака | F32: 10000
B51: =+SUM(B2:B50) -> 594 | C51: =+SUM(C2:C50) -> 594 | D51: =+SUM(D2:D50) -> 95 | F51: =+SUM(F2:F50) -> 48689
B53: Каракул | C53: =+B51-C51 -> 0
B54: Бнпз | C54: =+D51 -> 95
B55: Корхоно | C55: =+F51 -> 48689
B56: Итого | C56: =+SUM(C53:C55) -> 48784 | D56: =+C56*2900 -> 141473600

Sheet тогом
A1: Дата | B1: Ойбек пул берди | C1: Тогом юк берди | D1: Сабаб
A2: =B3-C3 -> -14976200
B3: =+SUM(B4:B10022) -> 1158731600 | C3: =+SUM(C4:C10022) -> 1173707800
A4: 28,02,2026 | C4: =4650*3600 -> 16740000 | D4: 4650*3600
A5: 5,03,2026 | B5: 16470000 | D5: мухи
B6: =750*3000 -> 2250000 | D6: 750*3 чугун
C7: =11590*3500 -> 40565000 | D7: 11590*3500
A8: 7,03,2026 | B8: =2500*12150 -> 30375000 | D8: 2500*12150
A9: 8,03,2026 | B9: 20000000 | C9: =9480*3500 -> 33180000 | D9: 9480*3500
A10: 10,03,2026 | B10: 22000000 | C10: =7780*3500 -> 27230000 | D10: 449 мошин,
A11: 11,03,2026 | C11: =4530*3200 -> 14496000 | D11: 4530*3200
A12: 12,03,2026 | B12: =1500*12100 -> 18150000 | C12: =4900*3600 -> 17640000 | D12: 4900*3600
A13: 13,03,2026 | B13: 24100000 | D13: 2000*12050
A14: 16,03,2026 | C14: =3930*3600 -> 14148000 | D14: 3930*3600
A15: 17,03,2026 | B15: 12050000 | C15: =4920*3600 -> 17712000 | D15: 1000*12050
A16: 18,03,2026 | B16: 25000000
A17: 19,03,2026 | C17: =5080*3600 -> 18288000 | D17: 5080*3600
A18: 21,03,2026 | C18: =4420*3600 -> 15912000 | D18: 4420*3600
A19: 22,03,2026 | B19: 12150000 | D19: 1000 $
A20: 23,03,2026 | B20: =2000*12050 -> 24100000 | D20: $ 2000*12050
C21: =5000*3600 -> 18000000 | D21: 5000*3600 мяхки
A22: 30,03,2026 | C22: =5180*3200 -> 16576000 | D22: 5180*3200
A23: 4,04,2026 | B23: 16000000 | D23: сум
C24: 3000000 | D24: релс
A25: 11,04,2026 | C25: =126*3500 -> 441000 | D25: 126 кг
A26: 15,04,2026 | C26: =4400*3600 -> 15840000 | D26: 4400*3600
A27: 16,04,2026 | B27: 7000000
B28: =1300*12150 -> 15795000
A29: 17,04,2026 | C29: =3580*3600 -> 12888000 | D29: 3580*3600
A30: 18,04,2026 | B30: =1500*12140 -> 18210000
A31: 19,04,2026 | C31: =4680*3600 -> 16848000 | D31: 4680*3600
A32: 21,04,2026 | B32: 20000000 | D32: СУМ
A33: 22,04,2026 | B33: 20000000 | C33: =6480*3600 -> 23328000 | D33: 6480*3600
A34: 23,04,2026 | C34: =4370*3200 -> 13984000 | D34: 4370*3200
A35: 23,04,2026 | C35: =4940*3600 -> 17784000 | D35: 4940*3600
A36: 25,04,2026 | B36: 30000000 | C36: =4080*3600 -> 14688000 | D36: 4080*3600
A37: 27,04,2026 | B37: 12000000 | D37: 1000*12000 $
A38: 29,04,2026 | B38: 2520000 | D38: ФАРУГ
A39: 30,04,2026 | C39: =10150*3500 -> 35525000 | D39: 10150*3500 | E39: 3700$ ТОГОМ
A40: 30,04,2026 | B40: 23900000 | D40: 2000$ | E40: 300$ Ойбек | G40: 5,05,2026
A41: 3,04,2026 | C41: =3890*3500 -> 13615000 | D41: 3890*3500
C42: 1200000 | D42: мурод
A43: 04,04,26 | B43: =1300*11970 -> 15561000 | D43: 1300$
C44: 1000000 | D44: Язна
C45: 800000 | D45: Мурод
A46: 5,04,2026 | B46: 15000000 | C46: 1000
A47: 6,05,2026 | C47: =7900*3500 -> 27650000 | D47: 7900*3500
A48: 7,05,2026 | B48: =890*3200 -> 2848000 | D48: 890*3200
C49: 4000000 | D49: релс расход
A50: 8,05,2026 | B50: 12100000 | D50: 1000 $
A51: 11,05,2026 | B51: =2200*12130 -> 26686000 | D51: 2200*12130
C52: =6490*3500 -> 22715000 | D52: 6490*3500
A53: 13,02,2026 | B53: 12000000
A54: 14,05,2026 | B54: =2500*12000 -> 30000000 | D54: 2500*12000 $
C55: =13050*3500 -> 45675000 | D55: 13050*3500
A56: 15,05,2026 | C56: =3250*3250 -> 10562500 | D56: 3250*3250
B57: =1500*11940 -> 17910000 | D57: 1500*11940
A58: 17,05,2026 | B58: 20000000 | D58: сум
C59: 1400000 | D59: мурод
A60: 19,05,2026 | C60: =10220*3500 -> 35770000 | D60: 10220*3500
A61: 20,05,2026 | B61: 30000000 | C61: =5940*3250 -> 19305000 | D61: 5940*3250
A62: 22,05,2026 | B62: 10000000 | D62: су м
A63: 25,05,2026 | B63: 24331500 | D63: СУМ
C64: =11830*3500 -> 41405000 | D64: 11830*3500
C65: 118000 | D65: КОЛЯ
C66: 48000 | D66: УЛУГБЕК
A67: 28,05,2026 | B67: 25000000 | D67: сум
C68: 1300000 | D68: мурод
A69: 01,06,26 | B69: 14000000 | C69: =10060*3500 -> 35210000 | D69: 10060*3500
B70: =300*12000 -> 3600000 | D70: 300$
A71: 5,06,2026 | B71: 12000000 | D71: 1000 $
A72: 6,06,2026 | C72: =2040*3300 -> 6732000 | D72: 2040*3300
C73: =6740*3500 -> 23590000 | D73: 6740*3500
A74: 7,06,2026 | B74: =1200*12000 -> 14400000 | D74: 1200 $
A75: 10,06,2026 | B75: 24000000 | D75: нурбек
A76: 28,06,2026 | C76: =1790*3300 -> 5907000 | D76: 1790*3300
A77: 30,06,2026 | B77: 8800000 | D77: нурбек
B78: 12000000 | D78: онем
C79: 900000 | D79: шохи
C80: 1000000 | D80: шохи
A81: 23,07,2026 | C81: =5150*3700 -> 19055000 | D81: 5150*3700
B82: 21465000
A83: 25,07,2026 | C83: 1200000
A84: 28,07,2026 | C84: 900000 | D84: шохи
A85: 01,08,26 | C85: 900000 | D85: шохи
A86: 3,08,2026 | C86: =5230*3720 -> 19455600 | D86: 5230*3720
A87: 4,07,2026 | B87: 22455600
A88: 7,08,2026 | C88: =2080*3300 -> 6864000 | D88: 2080*3300
B89: =1690*3300 -> 5577000 | D89: 1690*3300
B90: =2570*3300 -> 8481000 | D90: 2570*3300
A91: 10,08,2026 | B91: 11930000 | D91: 1000$
C92: =9450*3500 -> 33075000 | D92: 9450*3500
A93: 11,08,2026 | B93: 23800000 | D93: 2000$
C94: 1200000 | D94: шохи
A95: 13,08,2026 | C95: =10160*3550 -> 36068000 | D95: 10160*3550
B96: 11900000 | D96: 1000$
B97: 10000000 | D97: сум
A98: 16,08,2026 | B98: 11900000 | D98: нурбек
A99: 20,08,2026 | B99: =1670*3300 -> 5511000 | D99: 1670*3300
A100: 21,08,2026 | C100: 100000
...

Sheet Гостиница
A1: Дата | B1: Расход сумма | C1: Расход Наименование
B3: Жами Расход | C3: =+SUM(B4:B10040) -> 0
A5: Итого | C5: =340645+22828+17092+30606+C14 -> 429829
C6: 2022-2025 расход 293,000 $$$
A7: 31,01,2026 | C7: 14242
A8: 28,02,2026 | C8: =214150000/12150 -> 17625.514
A9: 31,03,2026 | C9: $15 777
A10: 31,03,2026 | C10: 568,820,000__ 46624$
A11: 30,04,26 | C11: 22828
A12: 31,05,26 | C12: 17092
A13: 46203 | C13: 30606
A14: 46234 | C14: 18658
C15: 430,000 $ обши расход
C21: саехат 24000000
C22: 900 $ 10,000,000
C23: бохча 1500,000

Sheet Бонусча
C2: Сабаб | D2: Ойбек | E2: ТОНН | F2: Цена | G2: Хитой бонусча
D3: =+SUM(D4:D34) -> 0 | E3: =+SUM(E4:E34) -> 0 | G3: =+SUM(G4:G34) -> 0 | H3: Ойбек пул берди | I3: =+D3 -> 0
B4: 46204 | G4: =+E4*F4 -> 0 | H4: =+G2 -> Хитой бонусча | I4: =+G3 -> 0
B5: =+B4+1 -> 46205 | G5: =+E5*F5 -> 0
B6: =+B5+1 -> 46206 | G6: =+E6*F6 -> 0
B7: =+B6+1 -> 46207 | G7: =+E7*F7 -> 0 | H7: Делта | I7: =+I3-I4+I5 -> 0
B8: =+B7+1 -> 46208 | G8: =+E8*F8 -> 0
B9: =+B8+1 -> 46209 | G9: =+E9*F9 -> 0
B10: =+B9+1 -> 46210 | G10: =+E10*F10 -> 0
B11: =+B10+1 -> 46211 | G11: =+E11*F11 -> 0
B12: =+B11+1 -> 46212 | G12: =+E12*F12 -> 0
B13: =+B12+1 -> 46213 | G13: =+E13*F13 -> 0
B14: =+B13+1 -> 46214 | G14: =+E14*F14 -> 0
B15: =+B14+1 -> 46215 | G15: =+E15*F15 -> 0
B16: =+B15+1 -> 46216 | G16: =+E16*F16 -> 0
B17: =+B16+1 -> 46217 | G17: =+E17*F17 -> 0
B18: =+B17+1 -> 46218 | G18: =+E18*F18 -> 0
B19: =+B18+1 -> 46219 | G19: =+E19*F19 -> 0
... B34: =+B33+1 -> 46234 | G34: =+E34*F34 -> 0

Sheet Чугун
B2: № | C2: Дата | D2: Сабаб | E2: Райим пул берди | F2: Рахим расход | G2: Мошин номер | H2: Брутто | I2: Нетто | J2: ТОНН | K2: Скидка | L2: После скидка | M2: Цена | N2: Навои Металл | O2: Тура ака
E3: =+SUM(E4:E13) -> 0 | F3: =+SUM(F4:F13) -> 0 | J3: =+SUM(J4:J16) -> 0 | L3: =+SUM(L4:L16) -> 0 | N3: =+SUM(N4:N16) -> 0 | O3: =+SUM(O4:O16) -> 0
B4: 1 | J4: =+H4-I4 -> 0 | L4: =+J4-(J4*K4/100) -> 0 | N4: =+(J4-J4*K4/100)*M4 -> 0
B5: 2 | J5: =+H5-I5 -> 0 | L5: =+J5-(J5*K5/100) -> 0 | N5: =+(J5-J5*K5/100)*M5 -> 0
B6: =+B5+1 -> 3 | J6: =+H6-I6 -> 0 | L6: =+J6-(J6*K6/100) -> 0 | N6: =+(J6-J6*K6/100)*M6 -> 0
B7: =+B6+1 -> 4 | J7: =+H7-I7 -> 0 | L7: =+J7-(J7*K7/100) -> 0 | N7: =+(J7-J7*K7/100)*M7 -> 0
B8: =+B7+1 -> 5 | J8: =+H8-I8 -> 0 | L8: =+J8-(J8*K8/100) -> 0 | N8: =+(J8-J8*K8/100)*M8 -> 0
B9: =+B8+1 -> 6 | J9: =+H9-I9 -> 0 | L9: =+J9-(J9*K9/100) -> 0 | N9: =+(J9-J9*K9/100)*M9 -> 0
B10: =+B9+1 -> 7 | J10: =+H10-I10 -> 0 | L10: =+J10-(J10*K10/100) -> 0 | N10: =+(J10-J10*K10/100)*M10 -> 0
B11: =+B10+1 -> 8 | J11: =+H11-I11 -> 0 | L11: =+J11-(J11*K11/100) -> 0 | N11: =+(J11-J11*K11/100)*M11 -> 0
B12: =+B11+1 -> 9 | J12: =+H12-I12 -> 0 | L12: =+J12-(J12*K12/100) -> 0 | N12: =+(J12-J12*K12/100)*M12 -> 0
B13: =+B12+1 -> 10 | J13: =+H13-I13 -> 0 | L13: =+J13-(J13*K13/100) -> 0 | N13: =+(J13-J13*K13/100)*M13 -> 0
B14: =+B13+1 -> 11 | J14: =+H14-I14 -> 0 | L14: =+J14-(J14*K14/100) -> 0 | N14: =+(J14-J14*K14/100)*M14 -> 0
B15: =+B14+1 -> 12 | J15: =+H15-I15 -> 0 | L15: =+J15-(J15*K15/100) -> 0 | N15: =+(J15-J15*K15/100)*M15 -> 0
B16: =+B15+1 -> 13 | J16: =+H16-I16 -> 0 | L16: =+J16-(J16*K16/100) -> 0 | N16: =+(J16-J16*K16/100)*M16 -> 0
C17: Ойбек пул берди | D17: =+E3 -> 0
C18: =+N2 -> Навои Металл | D18: =+N3 -> 0
C19: Рахим НАВОИ | D19: =+D17-D18 -> 0
C20: Металл сотилди | D20: =+O3 -> 0
C21: =+F2 -> Рахим расход | D21: =+F3 -> 0
C22: Делта | D22: =+D20-D18-D21 -> 0
B26: № | C26: Дата | D26: Сабаб | E26: Сумма Олинди | F26: Мошин номер | G26: Мошин пули | H26: Брутто | I26: Нетто | J26: ТОНН | K26: Скидка | L26: После скидка | M26: Цена | N26: Чугун
E27: =+SUM(E28:E37) -> 0 | F27: 200 | G27: =+SUM(G28:G40) -> 0 | J27: =+SUM(J28:J40) -> 0 | L27: =+SUM(L28:L40) -> 0 | N27: =+SUM(N28:N40) -> 0 | O27: Тура ака пул берди | P27: =+E27 -> 0
B28: 1 | G28: =+J28*9 -> 0 | J28: =+H28-I28 -> 0 | L28: =+J28-(J28*K28/100) -> 0 | N28: =+(J28-J28*K28/100)*M28 -> 0 | O28: =+N26 -> Чугун | P28: =+N27 -> 0
B29: 2 | G29: =+J29*9 -> 0 | J29: =+H29-I29 -> 0 | L29: =+J29-(J29*K29/100) -> 0 | N29: =+(J29-J29*K29/100)*M29 -> 0 | O29: Делта | P29: =+P27-P28 -> 0
B30: =+B29+1 -> 3 | G30: =+J30*9 -> 0 | J30: =+H30-I30 -> 0 | L30: =+J30-(J30*K30/100) -> 0 | N30: =+(J30-J30*K30/100)*M30 -> 0
B31: =+B30+1 -> 4 | G31: =+J31*9 -> 0 | J31: =+H31-I31 -> 0 | L31: =+J31-(J31*K31/100) -> 0 | N31: =+(J31-J31*K31/100)*M31 -> 0
B32: =+B31+1 -> 5 | G32: =+J32*9 -> 0 | J32: =+H32-I32 -> 0 | L32: =+J32-(J32*K32/100) -> 0 | N32: =+(J32-J32*K32/100)*M32 -> 0
B33: =+B32+1 -> 6 | G33: =+J33*9 -> 0 | J33: =+H33-I33 -> 0 | L33: =+J33-(J33*K33/100) -> 0 | N33: =+(J33-J33*K33/100)*M33 -> 0
B34: =+B33+1 -> 7 | G34: =+J34*9 -> 0 | J34: =+H34-I34 -> 0 | L34: =+J34-(J34*K34/100) -> 0 | N34: =+(J34-J34*K34/100)*M34 -> 0
B35: =+B34+1 -> 8 | G35: =+J35*9 -> 0 | J35: =+H35-I35 -> 0 | L35: =+J35-(J35*K35/100) -> 0 | N35: =+(J35-J35*K35/100)*M35 -> 0
B36: =+B35+1 -> 9 | G36: =+J36*9 -> 0 | J36: =+H36-I36 -> 0 | L36: =+J36-(J36*K36/100) -> 0 | N36: =+(J36-J36*K36/100)*M36 -> 0
B37: =+B36+1 -> 10 | G37: =+J37*9 -> 0 | J37: =+H37-I37 -> 0 | L37: =+J37-(J37*K37/100) -> 0 | N37: =+(J37-J37*K37/100)*M37 -> 0
B38: =+B37+1 -> 11 | G38: =+J38*9 -> 0 | J38: =+H38-I38 -> 0 | L38: =+J38-(J38*K38/100) -> 0 | N38: =+(J38-J38*K38/100)*M38 -> 0
B39: =+B38+1 -> 12 | G39: =+J39*F27 -> 0 | J39: =+H39-I39 -> 0 | L39: =+J39-(J39*K39/100) -> 0 | N39: =+(J39-J39*K39/100)*M39 -> 0
B40: =+B39+1 -> 13 | G40: =+J40*F27 -> 0 | J40: =+H40-I40 -> 0 | L40: =+J40-(J40*K40/100) -> 0 | N40: =+(J40-J40*K40/100)*M40 -> 0
